pypewriter/__init__.py
pypewriter/Pypewriter.py
pypewriter-0.1.0.dist-info/METADATA
pypewriter-0.1.0.dist-info/WHEEL
pypewriter-0.1.0.dist-info/RECORD
