Metadata-Version: 2.3
Name: pypewriter
Version: 0.1.0
Summary: Typewriter effect for your terminal
License: MIT
Requires-Python: >=3.13
Classifier: License :: OSI Approved :: MIT License
Classifier: Programming Language :: Python :: 3
Classifier: Programming Language :: Python :: 3.13
